kkTools/__init__.py
kkTools/audio.py
kkTools/calcTools.py
kkTools/calc_mcd.py
kkTools/checkTools.py
kkTools/cut_wav_fix_lab.py
kkTools/dirTools.py
kkTools/durTools.py
kkTools/fileTools.py
kkTools/jsonTools.py
kkTools/labelTools.py
kkTools/mosTools.py
kkTools/multiTask.py
kkTools/nlpTools.py
kkTools/npTools.py
kkTools/plotTools.py
kkTools/scpTools.py
kkTools/spkTools.py
kkTools/svsTools.py
kkTools/tools.py
kkTools/txtTools.py
kkTools/wavTools.py
kkcode-0.0.8.dist-info/LICENCE
kkcode-0.0.8.dist-info/METADATA
kkcode-0.0.8.dist-info/WHEEL
kkcode-0.0.8.dist-info/top_level.txt
kkcode-0.0.8.dist-info/RECORD
