Metadata-Version: 2.1
Name: kkcode
Version: 0.0.8
Summary: Some useful script for personal daily work.
Home-page: https://gitee.com/kksuperr/kkcode
Author: Hanzhao Li
Author-email: lihanzhao.mail@gmail.com
License: MIT
Classifier: Programming Language :: Python :: 3
Classifier: License :: OSI Approved :: MIT License
Classifier: Operating System :: OS Independent
Requires-Python: >=3.6
License-File: LICENCE
Requires-Dist: numpy
